{
    "cards" :
    [
        {
            "id" : "1",
            "task" : "SURPRISE ATTACK! Ανάγκασε κάποιον να πιει αντί για σένα!"
        },
        {
            "id" : "2",
            "task" : "ΠΙΝΕΙΣ!"
        },
        {
            "id" : "3",
            "task" : "Όποιος έχει ράμματα πίνει!"
        },
        {
            "id" : "4",
            "task" : "Αν έχεις σπάσει ποτέ σου κάποιο μέρος του σώματος σου πιες!"
        },
        {
            "id" : "5",
            "task" : "Όσοι οδηγούν μηχανή πίνουν."
        },
        {
            "id" : "6",
            "task" : "Όσοι έχουν κάνει skateboard πίνουν"
        },
        {
            "id" : "7",
            "task" : "Όποιος έχει κάνει ελεύθερη πτώση πίνει."
        },
        {
            "id" : "8",
            "task" : "SURPRISE ATTACK! Ανάγκασε κάποιον να πιει αντί για σένα!"
        },
        {
            "id" : "9",
            "task" : "ΓΟΥΤΣΟΥ ΓΟΥΤΣΟΥ! Μπορείς να χρησιμοποιήσεις αυτήν την κάρτα ώστε να αναγκάσεις κάποιον να πιει μαζί σου."
        },
        {
            "id" : "10",
            "task" : "Αν έχεις κάνεις ποτέ σου bungee jumping είναι ώρα να πιεις!"
        },
        {
            "id" : "11",
            "task" : "Όποιος έχει περάσει με κόκκινο φανάρι πίνει."
        },
        {
            "id" : "12",
            "task" : "Όποιος έχει κάνει ορειβασία πίνει."
        },
        {
            "id" : "13",
            "task" : "Όποιος έχει κάνει χόρτο πίνει!"
        },
        {
            "id" : "14",
            "task" : "Όποιος έχει κάνει κάποιου είδους ναρκωτικά πίνει."
        },
        {
            "id" : "15",
            "task" : "Όποιος έχει κάνει κατάδυση πίνει."
        },
        {
            "id" : "16",
            "task" : "Όσοι έχουν παίξει strip poker πίνουν."
        },
        {
            "id" : "17",
            "task" : "SURPRISE ATTACK! Ανάγκασε κάποιον να πιει αντί για σένα!"
        },
        {
            "id" : "18",
            "task" : "Όσοι έχουν κάνει κόντρες με κάποιο όχημα πίνουν."
        },
        {
            "id" : "19",
            "task" : "Όσοι έχουν κάνει εμετό από το πολύ ποτό πίνουν."
        },
        {
            "id" : "20",
            "task" : "Όσοι φοβούνται τις αράχνες πίνουν."
        },
        {
            "id" : "21",
            "task" : "ΜΠΡΆΒΟ ΈΚΑΝΕΣ ΤΗΝ ΤΎΧΗ ΣΟΥ! Μπορείς να χρησιμοποιήσεις μία φορά αυτήν την κάρτα για να μην πιέις."
        },
        {
            "id" : "22",
            "task" : "Όσοι έχουν τατουάζ πίνουν!"
        },
        {
            "id" : "23",
            "task" : "Όσοι έχουν piercings στο σώμα τους πίνουν."
        },
        {
            "id" : "24",
            "task" : "Όποιος έχει ρίξει κάποιο αντικείμενο στην τουαλέτα πίνει!"
        },
        {
            "id" : "25",
            "task" : "Όποιος έχει πάθει τροφική δηλητηρίαση πίνει."
        },
        {
            "id" : "26",
            "task" : "ΜΠΡΆΒΟ ΈΚΑΝΕΣ ΤΗΝ ΤΎΧΗ ΣΟΥ! Μπορείς να χρησιμοποιήσεις μία φορά αυτήν την κάρτα για να μην πιέις."
        },
        {
            "id" : "27",
            "task" : "Αν έχεις κάνει ηλεκτρονικό τσιγάρο πιες!"
        },
        {
            "id" : "28",
            "task" : "ΠΙΝΕΙΣ!"
        },
        {
            "id" : "29",
            "task" : "Όσοι έχουν διαβάσει κάποιο βιβλίο με ερωτικό περιεχόμενο πίνει."
        },
        {
            "id" : "30",
            "task" : "Όποιος έχει διαβάσει βιβλίο με πάνω από 1000 σελίδες πίνει."
        },
        {
            "id" : "31",
            "task" : "Αν κάποιος παίκτης έχει φύγει από μαγαζί χωρίς να πληρώσει πίνει."
        },
        {
            "id" : "32",
            "task" : "Όσοι φοβούνται το σκοτάδι πίνουν!"
        },
        {
            "id" : "33",
            "task" : "Όσοι φοβούνται τους κλόουν πίνουν!"
        },
        {
            "id" : "34",
            "task" : "SURPRISE ATTACK! Ανάγκασε κάποιον να πιει αντί για σένα!"
        },
        {
            "id" : "35",
            "task" : "Όποιος έχει πάρει κλήση-πρόστιμο πίνει"
        },
        {
            "id" : "36",
            "task" : "Όποιος έχει μπει μέσα σε θέατρο ή κινηματογράφο χωρίς να πληρώσει πίνει."
        },
        {
            "id" : "37",
            "task" : "Όσοι έχουν βγάλει πάνω από 5 selfies στη σειρά πίνουν."
        },
        {
            "id" : "38",
            "task" : "Όσους τους έχουν κλέψει το κινητό πίνουν."
        },
        {
            "id" : "39",
            "task" : "Όσοι έχουν κάνει skinny dipping πίνουν."
        },
        {
            "id" : "40",
            "task" : "ΓΟΥΤΣΟΥ ΓΟΥΤΣΟΥ! Μπορείς να χρησιμοποιήσεις αυτήν την κάρτα ώστε να αναγκάσεις κάποιον να πιει μαζί σου."
        },
        {
            "id" : "41",
            "task" : "Όποιος παίκτης έχει κάνει graffiti πίνει."
        },
        {
            "id" : "42",
            "task" : "Όποιος έχει χρησιμοποιήσει πυροσβεστήρα πίνει."
        },
        {
            "id" : "43",
            "task" : "Όποιος έχει ανάψει φωτιά πίνει."
        },
        {
            "id" : "44",
            "task" : "Άσπρο πάτο!"
        },
        {
            "id" : "45",
            "task" : "Όποιος έχει κάνει πατίνια πίνει."
        },
        {
            "id" : "46",
            "task" : "Όποιος έχει κάψει κάποιο αντικείμενο πίνουν."
        },
        {
            "id" : "47",
            "task" : "Όποιος έχει σκίσει κάποιο ρούχο του πίνει."
        },
        {
            "id" : "48",
            "task" : "Όποιος έχει οδηγήσει χωρίς δίπλωμα πίνει!"
        },
        {
            "id" : "49",
            "task" : "Όποιος έχει κατουρήσει μέσα σε μπουκάλι/ποτήρι πίνει."
        },
        {
            "id" : "50",
            "task" : "SURPRISE ATTACK! Κράτα αυτήν την κάρτα, μπορείς να την χρησιμοποιήσεις μόνο μία φορά μπορείς να αναγκάσεις όποιο άτομο θες να πιέι!!"
        },
        {
            "id" : "51",
            "task" : "ΘΑΡΡΟΣ 'Η ΘΑΡΡΟΣ: Ο διπλανός σου διαλέγει ένα άτομο να πας να του την πέσεις. Φλέρταρε ή πιες."
        },
        {
            "id" : "52",
            "task" : "ΘΑΡΡΟΣ 'Η ΘΑΡΡΟΣ: Πάρε ένα ποτήρι από διπλανό τραπέζι, αλλιώς πιες."
        },
        {
            "id" : "53",
            "task" : "ΘΑΡΡΟΣ 'Η ΘΑΡΡΟΣ: Δώσε πρόσβαση στο instagram σου στον παίκτη που βρίσκεται στα αριστερά σου για να ανεβάσει ότι θέλει. Αντίθετα πιες."
        },
        {
            "id" : "54",
            "task" : "ΘΑΡΡΟΣ 'Η ΘΑΡΡΟΣ: Δώσε πρόσβαση στο facebook σου στον παίκτη που βρίσκεται απέναντι σου για να ανεβάσει ότι θέλει. Αντίθετα πιες."
        },
        {
            "id" : "55",
            "task" : "ΘΑΡΡΟΣ 'Η ΘΑΡΡΟΣ: Δώσε πρόσβαση στο twitter σου στον παίκτη στα δεξιά σου για να ανεβάσει ότι θέλει. Αντίθετα πιες."
        },
        {
            "id" : "56",
            "task" : "ΘΑΡΡΟΣ 'Η ΘΑΡΡΟΣ: Δώσε το κινητό σου στον κοντινότερο σου παίκτη του αντίθετου φύλου για να στείλει μήνυμα σε όποια επαφή σου θέλει. Αλλιώς πιες. "
        },
        {
            "id" : "57",
            "task" : "ΘΑΡΡΟΣ 'Η ΘΑΡΡΟΣ: Πάρε τη μητέρα σου τηλέφωνο και δώσε στον δεξιό σου παίκτης να της μιλήσει. Αλλιώς πιες."
        },
        {
            "id" : "58",
            "task" : "ΓΟΥΤΣΟΥ ΓΟΥΤΣΟΥ! Μπορείς να χρησιμοποιήσεις αυτήν την κάρτα ώστε να αναγκάσεις κάποιον να πιει μαζί σου."
        },
        {
            "id" : "59",
            "task" : "ΘΑΡΡΟΣ 'Η ΘΑΡΡΟΣ: Εξομολόγησε τα αισθήματά σου σ' αυτόν/ην που σου αρέσει αλλιώς πιες."
        },
        {
            "id" : "60",
            "task" : "Αν υπάρχει παίκτης που να του αρέσει κάποιος από τους υπόλοιπους παίκτες πίνει."
        },
        {
            "id" : "61",
            "task" : "Αν υπάρχει παίκτης που νσ του άρεσε κάποιος από τους υπόλοιπους παίκτες πίνει."
        },
        {
            "id" : "62",
            "task" : "Στην υγεία σου!"
        },
        {
            "id" : "63",
            "task" : "Όσους τους έχουν βαρέσει στο πρόσωπο πίνουν."
        },
        {
            "id" : "64",
            "task" : "Όσοι έχουν χαστουκίσει κάποιον πίνουν."
        },
        {
            "id" : "65",
            "task" : "ΘΑΡΡΟΣ 'Η ΘΑΡΡΟΣ: Ανέβασε μία φωτογραφία με τα πόδια σου σε instagram story σου, αλλιώς πιεις."
        },
        {
            "id" : "66",
            "task" : "ΘΑΡΡΟΣ 'Η ΘΑΡΡΟΣ: Ανέβασε μία φωτογραφία τις παλάμες του διπλανού σου παίκτη σου με caption: \"Ας μου μαυρίσει τον ποπό και γω δικός του/της! \", αλλιώς πιες. "
        },
        {
            "id" : "67",
            "task" : "SURPRISE ATTACK! Ανάγκασε κάποιον να πιει αντί για σένα!"
        },
        {
            "id" : "68",
            "task" : "Περιέγραψε τη μέρα σου σήμερα χρησιμοποιώντας μόνο το \"Ι\" από φωνήεντα. Αν αποτύχεις πίνεις."
        },
        {
            "id" : "69",
            "task" : "Περιέγραψε τι φοράς σήμερα χρησιμοποιώντας μόνο το \"Ο\" από φωνήεντα. Αν αποτύχεις πίνεις."
        },
        {
            "id" : "70",
            "task" : "Περιέγραψε το πρόσωπο του παίκτη απέναντι σου χρησιμοποιώντας μόνο το \"Α\" από φωνήεντα. Αν αποτύχεις πίνεις."
        },
        {
            "id" : "71",
            "task" : "Φίλα στο μέτωπο τον δεξιό σου παίκτη ή ΠΙΕΣ!"
        },
        {
            "id" : "72",
            "task" : "Διάλεξε κάποιον τυχαίο και κλείσε του το μάτι. Αν δεν μπορείς ή δε θες πίνεις."
        },
        {
            "id" : "73",
            "task" : "Όσοι έχουν σηκώσει βάρη πίνουν."
        },
        {
            "id" : "74",
            "task" : "ΠΙΝΕΙΣ!"
        },
        {
            "id" : "75",
            "task" : "Όσοι λένε το σουβλάκι καλαμάκι ΠΙΝΟΥΝ!"
        },
        {
            "id" : "76",
            "task" : "Όποιος έχει κάνει κάτι με κάποιον που γνώρισε την ίδια μέρα πίνει!"
        },
        {
            "id" : "77",
            "task" : "ΘΑΡΡΟΣ 'Η ΘΑΡΡΟΣ: Ανέβασε story να κρατάς χαρτί τουαλέτας ή πιες!"
        },
        {
            "id" : "78",
            "task" : "ΓΟΥΤΣΟΥ ΓΟΥΤΣΟΥ! Μπορείς να χρησιμοποιήσεις αυτήν την κάρτα ώστε να αναγκάσεις κάποιον να πιει μαζί σου."
        },
        {
            "id" : "79",
            "task" : "Προσπάθησε να γλείψεις τον αγκώνα σου. Αν δεν τα καταφέρεις πίνεις!"
        },
        {
            "id" : "80",
            "task" : "ΘΑΡΡΟΣ 'Η ΘΑΡΡΟΣ: Χαστούκισε τον απέναντι παίκτη σου ή πιες."
        },
        {
            "id" : "81",
            "task" : "ΘΑΡΡΟΣ Ή ΘΑΡΡΟΣ: Γλείψε τη μύτη του παίκτη στ' αριστερά σου ή πιες."
        },
        {
            "id" : "82",
            "task" : "Όποιος έχει κολυμπήσει με τα ρούχα του πίνει."
        },
        {
            "id" : "83",
            "task" : "Όποιος έχει πει πως θα κόψει το τσιγάρο και δεν το 'κανε πίνει."
        },
        {
            "id" : "84",
            "task" : "ΜΠΡΆΒΟ ΈΚΑΝΕΣ ΤΗΝ ΤΎΧΗ ΣΟΥ! Μπορείς να χρησιμοποιήσεις μία φορά αυτήν την κάρτα για να μην πιέις."
        },
        {
            "id" : "85",
            "task" : "Όποιος έχει καταφέρει να κόψει το τσιγάρο ΜΠΡΑΒΟ. Ελεύθερος γύρος. Dεν πίνει κανείς."
        },
        {
            "id" : "86",
            "task" : "ΓΟΥΤΣΟΥ ΓΟΥΤΣΟΥ! Μπορείς να χρησιμοποιήσεις αυτήν την κάρτα ώστε να αναγκάσεις κάποιον να πιει μαζί σου."
        },
        {
            "id" : "87",
            "task" : "ΘΑΡΡΟΣ Ή ΘΑΡΡΟΣ: Πάνε βρέξε το πρόσωπό σου ή πιες."
        },
        {
            "id" : "88",
            "task" : "ΘΑΡΡΟΣ Ή ΘΑΡΡΟΣ: Κάνε το flosh ή πιες."
        },
        {
            "id" : "89",
            "task" : "ΘΑΡΡΟΣ Ή ΘΑΡΡΟΣ: Χόρεψε σαν τον Κάρλτον από το The Fresh Prince Of Bel-Air ή πιες."
        },
        {
            "id" : "90",
            "task" : "Όσοι παίκτες έχουν αρχίσει να νιώθουν μεθυσμένοι να σηκώσουν το χέρι τους. Οι υπόλοιποι πίνουν."
        },
        {
            "id" : "91",
            "task" : "ΜΠΡΆΒΟ ΈΚΑΝΕΣ ΤΗΝ ΤΎΧΗ ΣΟΥ! Μπορείς να χρησιμοποιήσεις μία φορά αυτήν την κάρτα για να μην πιέις."
        },
        {
            "id" : "92",
            "task" : "Ελεύθερος γύρος. Κανείς δεν πίνει."
        },
        {
            "id" : "93",
            "task" : "ΘΑΡΡΟΣ Ή ΘΑΡΡΟΣ: Δείξε σ' όλους τις τελευταίες 3 φωτογραφίες που έχεις στο κινητό σου ή πιες."
        },
        {
            "id" : "94",
            "task" : "Όποιος ακούει ξένα τραγούδια πίνει."
        },
        {
            "id" : "95",
            "task" : "Εσύ και 3 άλλοι παίκτες που θα διαλέξεις πρέπει να πιείτε χωρίς να χρησιμοποιήσετε τα χέρια σας. Αν έστω και ένας αποτύχει ξανά πίνετε."
        },
        {
            "id" : "96",
            "task" : "Μαζί με τον αριστερό σου παίκτη αναπαραστήστε την σκηνή του Τιτανικού: \"Jack I'm flying!\". Αλλιώς πίνετε και οι δύο."
        },
        {
            "id" : "97",
            "task" : "ΘΑΡΡΟΣ Ή ΘΑΡΡΟΣ: Σήκω και τραγούδα τον εθνικό ύμνο, αλλιώς πιες."
        },
        {
            "id" : "98",
            "task" : "ΤΟ ΠΑΤΩΜΑ ΕΙΝΑΙ ΛΑΒΑ: Ο τελευταίος παίκτης που θα γλιτώσει πίνει."
        },
        {
            "id" : "99",
            "task" : "SURPRISE ATTACK! Ανάγκασε κάποιον να πιει αντί για σένα!"
        },
        {
            "id" : "100",
            "task" : "ΘΑΡΡΟΣ Ή ΘΑΡΡΟΣ: Φτιάξε το αγαπημένο σου meme με σένα και ανέβασε το στα μέσα κοινωνικής δικτύωσης σου, αλλιώς πιες."
        },
        {
            "id" : "101",
            "task" : "ΘΑΡΡΟΣ Ή ΘΑΡΡΟΣ: Φτιάξε το αγαπημένο σου meme με σένα και ανέβασε το στα μέσα κοινωνικής δικτύωσης σου, αλλιώς πιες."
        },
        {
            "id" : "102",
            "task" : "ΘΑΡΡΟΣ Ή ΘΑΡΡΟΣ: Φτιάξε το αγαπημένο σου meme με σένα και ανέβασε το στα μέσα κοινωνικής δικτύωσης σου, αλλιώς πιες."
        },
        {
            "id" : "103",
            "task" : "ΘΑΡΡΟΣ Ή ΘΑΡΡΟΣ: Πάρε το ποτό από το διπλανό τραπέζι ή πιες."
        },
        {
            "id" : "104",
            "task" : "ΘΑΡΡΟΣ Ή ΘΑΡΡΟΣ: Τράβα το αυτί του δεξιού σου παίκτη ή πιες."
        },
        {
            "id" : "105",
            "task" : "Όλοι οι παίκτες γράφουν ένα μυστικό σε μια χαρτοπετσέτα και τις αφήνετε στη μέση. Όποιος ξανά τύχει τη δική του πίνει."
        },
        {
            "id" : "106",
            "task" : "ΓΟΥΤΣΟΥ ΓΟΥΤΣΟΥ! Μπορείς να χρησιμοποιήσεις αυτήν την κάρτα ώστε να αναγκάσεις κάποιον να πιει μαζί σου."
        },
        {
            "id" : "107",
            "task" : "Απλά πιες."
        },
        {
            "id" : "108",
            "task" : "ΘΑΡΡΟΣ Ή ΘΑΡΡΟΣ: Γράψε τον αριθμό σου σε μια χαρτοπετσέτα και δώσ' την κάποιον άγνωστο ή πιες."
        },
        {
            "id" : "109",
            "task" : "Κάνε πλεξούδα τα μαλλιά της κοντινότερης κοπέλας. Αν αποτύχεις πίνεις!"
        },
        {
            "id" : "110",
            "task" : "ΜΠΡΆΒΟ ΈΚΑΝΕΣ ΤΗΝ ΤΎΧΗ ΣΟΥ! Μπορείς να χρησιμοποιήσεις μία φορά αυτήν την κάρτα για να μην πιέις"
        },
        {
            "id" : "111",
            "task" : "ΘΑΡΡΟΣ Ή ΘΑΡΡΟΣ: Βγάλε τα παπούτσια σου, φόρα τα σα γάντια και προσπάθησε να σερβίρεις ένα ποτό στο διπλανό σου ή πιες."
        },
        {
            "id" : "112",
            "task" : "ΘΑΡΡΟΣ Ή ΘΑΡΡΟΣ: Μύρισε τη μασχάλη του αριστερού σου παίκτη ή πιες."
        },
        {
            "id" : "113",
            "task" : "ΘΑΡΡΟΣ Ή ΘΑΡΡΟΣ: Τραγούδησε το ρεφρέν από το \"Gucci φόρεμα\" του Μαζωνάκη ή πιες!"
        },
        {
            "id" : "114",
            "task" : "ΘΑΡΡΟΣ Ή ΘΑΡΡΟΣ: Τραγούδησε το ρεφρέν από το \"Woh\" του FY ή πιες!"
        },
        {
            "id" : "115",
            "task" : "ΘΑΡΡΟΣ Ή ΘΑΡΡΟΣ: Δείξε τον ποπό σου σ' όλους ή πιες."
        }
    ]
}